{
  "date": "2025-11-03",
  "source_url": "https://www.yalla-shoot.info/matches-today/",
  "matches": [
    {
      "id": "الغرافة-الهلال-2025-11-03",
      "home": "الغرافة",
      "away": "الهلال",
      "home_logo": "https://www.yalla-shoot.info/wp-content/uploads/2025/02/970.png",
      "away_logo": "https://www.yalla-shoot.info/wp-content/uploads/2025/01/269.png",
      "time_baghdad": "20:15",
      "status": "NS",
      "status_text": "جارية الان",
      "result_text": "0-0",
      "channel": "beIN SPORTS HD 1",
      "commentator": "غير معروف",
      "competition": "آسيا, دوري أبطال آسيا للنخبة",
      "_source": "yalla1shoot"
    },
    {
      "id": "لاتسيو-كالياري-2025-11-03",
      "home": "لاتسيو",
      "away": "كالياري",
      "home_logo": "https://www.yalla-shoot.info/wp-content/uploads/2025/01/136.png",
      "away_logo": "https://www.yalla-shoot.info/wp-content/uploads/2025/02/324.png",
      "time_baghdad": "21:45",
      "status": "NS",
      "status_text": "جارية الان",
      "result_text": "0-0",
      "channel": "غير معروف",
      "commentator": "غير معروف",
      "competition": "إيطاليا, الدوري الإيطالي",
      "_source": "yalla1shoot"
    },
    {
      "id": "سندرلاند-إيفرتون-2025-11-03",
      "home": "سندرلاند",
      "away": "إيفرتون",
      "home_logo": "https://www.yalla-shoot.info/wp-content/uploads/2025/08/117.png",
      "away_logo": "https://www.yalla-shoot.info/wp-content/uploads/2025/01/90.png",
      "time_baghdad": "22:00",
      "status": "NS",
      "status_text": "جارية الان",
      "result_text": "0-0",
      "channel": "Bein Sports HD2",
      "commentator": "غير معروف",
      "competition": "إنجلترا, الدوري الإنجليزي",
      "_source": "yalla1shoot"
    },
    {
      "id": "ريالأوفييدو-أوساسونا-2025-11-03",
      "home": "ريال أوفييدو",
      "away": "أوساسونا",
      "home_logo": "https://www.yalla-shoot.info/wp-content/uploads/2025/08/193.png",
      "away_logo": "https://www.yalla-shoot.info/wp-content/uploads/2025/02/118.png",
      "time_baghdad": "22:00",
      "status": "NS",
      "status_text": "جارية الان",
      "result_text": "0-0",
      "channel": "beIN Sports 3 HD",
      "commentator": "غير معروف",
      "competition": "إسبانيا, الدوري الإسباني",
      "_source": "yalla1shoot"
    },
    {
      "id": "ناسافكارشي-الوحدة-2025-11-03",
      "home": "ناساف كارشي",
      "away": "الوحدة",
      "home_logo": "https://www.yalla-shoot.info/wp-content/uploads/2025/09/8596.png",
      "away_logo": "https://www.yalla-shoot.info/wp-content/uploads/2025/01/876.png",
      "time_baghdad": "15:45",
      "status": "FT",
      "status_text": "انتهت",
      "result_text": "0-0",
      "channel": "beIN SPORTS HD 1",
      "commentator": "غير معروف",
      "competition": "آسيا, دوري أبطال آسيا للنخبة",
      "_source": "yalla1shoot"
    },
    {
      "id": "الدحيل-شبابالاهلي-2025-11-03",
      "home": "الدحيل",
      "away": "شباب الاهلي",
      "home_logo": "https://www.yalla-shoot.info/wp-content/uploads/2025/01/2034.png",
      "away_logo": "https://www.yalla-shoot.info/wp-content/uploads/2025/08/8347.png",
      "time_baghdad": "18:00",
      "status": "FT",
      "status_text": "انتهت",
      "result_text": "0-0",
      "channel": "beIN SPORTS HD 1",
      "commentator": "غير معروف",
      "competition": "آسيا, دوري أبطال آسيا للنخبة",
      "_source": "yalla1shoot"
    },
    {
      "id": "تراکتورسازي-الشرطة-2025-11-03",
      "home": "تراکتورسازي",
      "away": "الشرطة",
      "home_logo": "https://www.yalla-shoot.info/wp-content/uploads/2025/09/9353.png",
      "away_logo": "https://www.yalla-shoot.info/wp-content/uploads/2025/02/1218.png",
      "time_baghdad": "18:00",
      "status": "FT",
      "status_text": "انتهت",
      "result_text": "0-0",
      "channel": "Bein Sports HD2",
      "commentator": "غير معروف",
      "competition": "آسيا, دوري أبطال آسيا للنخبة",
      "_source": "yalla1shoot"
    },
    {
      "id": "ساسولو-جنوى-2025-11-03",
      "home": "ساسولو",
      "away": "جنوى",
      "home_logo": "https://www.yalla-shoot.info/wp-content/uploads/2025/08/266.png",
      "away_logo": "https://www.yalla-shoot.info/wp-content/uploads/2025/02/514.png",
      "time_baghdad": "19:30",
      "status": "FT",
      "status_text": "انتهت",
      "result_text": "0-0",
      "channel": "غير معروف",
      "commentator": "غير معروف",
      "competition": "إيطاليا, الدوري الإيطالي",
      "_source": "yalla1shoot"
    }
  ]
}